Metadata-Version: 2.1
Name: pymechanism
Version: 1.1
Summary: Simulation of the H2Global Mechanism
Author: Julian Reul
Author-email: julian.reul@h2-global.org
License: MIT
License-File: LICENSE.txt
